dtreenetwork-1.2.1.dist-info/licenses/LICENSE
tests/__init__.py
tests/test_model.py
treenet/__init__.py
treenet/model.py
dtreenetwork-1.2.1.dist-info/METADATA
dtreenetwork-1.2.1.dist-info/WHEEL
dtreenetwork-1.2.1.dist-info/top_level.txt
dtreenetwork-1.2.1.dist-info/RECORD
