Metadata-Version: 2.4
Name: dtreenetwork
Version: 1.2.1
Summary: A Layered Decision Tree Based Model for Classification tasks
Home-page: https://github.com/zeshanalvi/treenet
Author: Zeshan Khan
Author-email: zeshankhanalvi@gmail.com
License: MIT
Requires-Python: >=3.8
License-File: LICENSE
Requires-Dist: numpy>=1.20
Dynamic: license-file
